{"avatarLinks": "https://images.gog.com/48689112ea1e614b099a281ef23c76087e1a1a94bbdba2492dbd59b7ce1fa560_avs.jpg , https://images.gog.com/48689112ea1e614b099a281ef23c76087e1a1a94bbdba2492dbd59b7ce1fa560_avs2.jpg 2x"}{"Total number of games": 233}{"Iron Harvest": "49.99", "Divinity: Original Sin 2 - Sir Lora": "2.19", "Pathfinder: Kingmaker - Season Pass Bundle": "14.19", "Outward": "19.99", "Outward: The Soroboreans": "17.99", "Mutant Year Zero: Road to Eden - Deluxe Edition": "17.99", "Tower Hunter: Erza's Trial": "14.99", "Hellmut: The Badass from Hell": "14.99", "Streets of Rage 4": "24.99", "Crysis Warhead\u00ae": "4.59", "Spiritfarer": "24.99", "Frostpunk: Game of the Year edition": "32.49", "Frostpunk: On The Edge": "12.99", "Kingdoms of Amalur: Re-Reckoning": "0", "Littlewood": "12.49", "Overlord II": "8.99", "Baldur's Gate II: Enhanced Edition": "8.39", "Baldur's Gate: Faces of Good and Evil": "0.49", "Baldur's Gate: Enhanced Edition": "8.39", "The Incredible Adventures of Van Helsing: Final Cut": "44.99", "LEGO\u00ae Indiana Jones\u2122: The Original Adventures": "16.79", "LEGO\u00ae Star Wars\u2122 III - The Clone Wars\u2122": "16.79", "Outcast - Second Contact": "6.99", "Fury Unleashed": "19.99", "Bite the Bullet": "9.39", "Men of War: Assault Squad": "1.69", "Dead Space\u2122": "5.09", "Crysis\u00ae": "4.59", "BioShock Infinite Complete Edition": "13.79", "INMOST": "12.99", "Knightin'+": "4.99", "Alwa's Awakening": "9.99", "Exit the Gungeon": "6.19", "Alwa's Legacy": "14.99", "Ittle Dew": "8.39", "Serious Sam's Bogus Detour": "7.49", "Iron Harvest Deluxe Edition": "69.89", "Realms Beyond: Ashes of the Fallen": "0", "Windbound": "29.99", "Resolutiion": "19.99", "Caveblazers": "9.99", "Cat Quest II": "14.99", "Cat Quest": "12.99", "Metro Exodus": "19.99", "Asura: Vengeance Edition": "9.99", "EARTHLOCK": "24.99", "Timespinner": "19.99", "KUNAI": "16.99", "Cathedral": "13.99", "Headlander": "19.99", "Dandara: Trials of Fear Edition": "5.99", "Rogue Legacy": "12.59", "Shantae and the Seven Sirens": "24.99", "Asterix & Obelix XXL 3 - The Crystal Menhir": "15.09", "Asterix & Obelix XXL 2": "8.99", "My Friend Pedro": "10.09", "Blazing Beaks": "14.99", "Ghost of a Tale": "22.99", "Destroy All Humans!": "29.99", "Biped": "9.29", "Timelie": "15.99", "Titan Quest: Atlantis": "14.99", "SpongeBob SquarePants: Battle for Bikini Bottom - Rehydrated": "29.99", "Summer in Mara": "21.99", "Slime Rancher": "16.79", "River City Ransom: Underground": "19.99", "Sparklite": "24.99", "Minoria": "14.29", "Universe Sandbox": "24.99", "Streets of Rogue": "11.79", "Children of Morta": "13.19", "Niffelheim": "16.79", "Overcooked! 2": "13.79", "Darksiders Genesis": "29.99", "Unruly Heroes": "19.99", "Stranded Sails - Explorers of the Cursed Islands": "12.59", "Underrail: Expedition": "9.99", "Valfaris": "20.99", "River City Girls": "24.99", "Pine": "20.99", "Space Robinson: Hardcore Roguelike Action": "8.19", "Indivisible": "23.99", "Noita": "18.99", "Stygian: Reign of the Old Ones": "6.29", "This War of Mine Stories - Fading Embers": "3.99", "This War of Mine: Stories - Father's Promise": "1.49", "This War of Mine: The Little Ones": "2.09", "This War of Mine: Stories - The Last Broadcast": "2.79", "Xeno Crisis": "17.99", "Crying Suns": "14.69", "Blasphemous": "13.79", "Creature in the Well": "12.49", "Nine Parchments": "5.09", "They Are Billions": "29.99", "Trine 4: The Nightmare Prince": "8.99", "Little Nightmares": "19.99", "DARQ": "16.79", "Slay the Spire": "20.99", "Ion Fury": "20.99", "The Great Perhaps": "2.59", "Zombotron": "12.49", "Age of Wonders: Planetfall": "25.09", "Train Valley 2": "12.49", "House Flipper": "16.79", "Cyberpunk 2077": "59.99", "Monster Boy and the Cursed Kingdom": "29.99", "Warlocks 2: God Slayers": "19.99", "Eagle Island": "16.79", "Odallus: The Dark Call": "8.39", "Oniken: Unstoppable Edition": "4.99", "Monster Jam Steel Titans": "29.99", "AMID EVIL": "10.19", "Bloodstained: Ritual of the Night": "23.99", "Seasons after Fall": "9.99", "Pier Solar and the Great Architects": "12.59", "Shadows: Awakening": "10.00", "My Time At Portia": "11.99", "Prince of Persia": "3.39", "Thea 2: The Shattering": "21.99", "A Hat in Time - Nyakuza Metro": "3.99", "Shaq Fu: A Legend Reborn": "19.99", "S.W.I.N.E. HD Remaster": "9.99", "Blood: Fresh Supply": "8.19", "Dark Devotion": "19.99", "Mutant Year Zero: Road to Eden": "13.99", "Cossacks II Anthology": "2.09", "Katana ZERO": "8.39", "Star Control\u00ae: Origins": "24.99", "Megabyte Punch": "12.59", "Oddworld: New \u2019n\u2019 Tasty": "19.99", "Oddworld: New 'n' Tasty - Alf's Escape": "2.99", "Oddworld: Munch's Oddysee": "4.99", "Oddworld: Stranger's Wrath HD": "8.39", "Guacamelee! 2": "19.99", "Titan Quest: Ragnar\u00f6k": "19.99", "Tyranny - Standard Edition": "10.19", "Rage of Mages II: Necromancer": "5.09", "Rage of Mages": "5.09", "Rad Rodgers Radical Edition": "19.99", "Overcooked: Gourmet Edition": "4.79", "Legend of Kay: Anniversary": "19.99", "Flower": "3.49", "AWAY: Journey to the Unexpected": "11.39", "Blazing Chrome": "16.99", "ATOM RPG: Post-apocalyptic indie game": "10.49", "TANGLEWOOD\u00ae": "14.99", "Retro City Rampage DX": "14.99", "Westerado: Double Barreled": "14.99", "Never Alone Arctic Collection": "15.19", "Mana Spark": "8.19", "Space Rangers HD: A War Apart": "3.19", "Trailblazers": "29.99", "Carmageddon: Max Damage": "16.99", "Worms W.M.D": "7.49", "Momodora: Reverie Under the Moonlight": "8.39", "Guns, Gore & Cannoli 2": "12.99", "Apotheon": "12.59", "Nuclear Throne": "10.09", "La-Mulana": "12.59", "La-Mulana 2": "20.99", "Thea: The Awakening": "19.99", "BioShock\u2122 2 Remastered": "5.09", "BioShock\u2122 Remastered": "5.09", "Pillars of Eternity II: Deadfire": "19.99", "Pillars of Eternity: Hero Edition": "13.99", "Bloodrayne: Betrayal": "9.99", "Planescape: Torment: Enhanced Edition": "10.00", "Fictorum": "8.19", "Neverwinter Nights 2 Complete": "16.79", "Braid": "14.99", "INSIDE": "16.79", "The Witness": "36.99", "Heroes of Might and Magic\u00ae 5: Bundle": "5.00", "Heroes of Might and Magic\u00ae 3: Complete": "2.49", "BATTLETECH": "10.00", "THE KING OF FIGHTERS XIII GALAXY EDITION": "19.99", "Freedom Planet": "12.59", "The First Tree": "9.99", "Kynseed": "8.39", "Valdis Story: Abyssal City": "12.59", "Mutant Football League: Dynasty Edition": "16.49", "Papers, Please": "8.99", "The Mummy Demastered": "19.99", "Starbound": "13.99", "Cornerstone: The Song of Tyrim": "19.99", "Kingdom Rush: Frontiers": "9.99", "Kingdom Rush Origins": "12.49", "Kingdom Rush": "8.39", "Biomutant": "0", "Mark of the Ninja": "12.59", "Aragami": "19.99", "Project Warlock": "4.39", "Grim Dawn": "24.99", "Shantae: Risky's Revenge - Director's Cut": "8.39", "Shantae and the Pirate's Curse": "19.99", "Shantae: Half-Genie Hero Ultimate Edition": "24.99", "Breathedge": "16.79", "Kerbal Space Program": "10.00", "Graveyard Keeper": "8.39", "Banner Saga 2": "24.99", "Banner Saga 3": "24.99", "Banner Saga": "24.99", "Pathfinder: Kingmaker - Explorer Edition": "15.00", "Lovecraft's Untold Stories": "14.99", "SteamWorld Dig 2": "7.99", "SteamWorld Heist": "3.79", "Victor Vran: Mot\u00f6rhead - Through the Ages": "2.49", "Victor Vran: Fractured Worlds": "2.49", "Victor Vran": "5.99", "Frostpunk": "11.99", "A Hat in Time - Seal the Deal": "4.99", "CrossCode": "19.99", "Rezrog": "3.09", "Songbringer": "19.99", "Darkest Dungeon\u00ae": "22.99", "Epistory - Typing Chronicles": "14.99", "Divinity: Original Sin 2 - Definitive Edition": "22.49", "The Swords of Ditto: Mormo\u2019s Curse": "6.29", "Mages of Mystralia": "19.99", "Mulaka": "19.99", "Terraria": "9.99", "Stardew Valley": "13.99", "Enter the Gungeon": "7.49", "Rayman Origins": "3.39", "Dead Cells": "24.99", "Battle Chasers: Nightwar": "29.99", "Owlboy": "20.99", "Wizard of Legend": "15.99", "Heroes of Hammerwatch": "11.99", "Death's Gambit": "19.99", "Shovel Knight: Treasure Trove": "39.99", "Cuphead": "19.99", "The Messenger": "8.39"}{"Total price": "3460.56"}